{
  "with": {
    "codeSize": 23.137,
    "responseTime": 5600.631,
    "responseSize": 203.524,
    "requestCount": 357,
    "answerRate": 1,
    "overheadTime": 2888.054,
    "didFetchData": true,
    "codeSize**": null,
    "responseTime**": null,
    "responseSize**": null,
    "requestCount**": null,
    "answerRate**": null,
    "codeAdded**": null,
    "codeRemoved**": null
  },
  "without": {
    "codeSize": 16.794,
    "responseTime": 5600.631,
    "responseSize": 203.524,
    "requestCount": 357,
    "answerRate": 1,
    "overheadTime": 0,
    "didFetchData": true,
    "codeSize**": null,
    "responseTime**": null,
    "responseSize**": null,
    "requestCount**": null,
    "answerRate**": null,
    "codeAdded**": null,
    "codeRemoved**": null
  }
}
